{
  "subject": "MLT",
  "weeks": {
    "Week 1": [
      {
        "id": "1.1 Introduction to Machine Learning",
        "title": "1.1 Introduction to Machine Learning",
        "link": "https://www.youtube.com/watch?v=KMcUe7GQnf0"
      },
      {
        "id": "1.2 Paradigms of Machine Learning",
        "title": "1.2 Paradigms of Machine Learning",
        "link": "https://www.youtube.com/watch?v=ipjggYk7zXs"
      },
      {
        "id": "1.3 Representation Learning",
        "title": "1.3 Representation Learning: Part 1",
        "link": "https://www.youtube.com/watch?v=1V_M4JxygGk"
      },
      {
        "id": "1.4 Representation Learning",
        "title": "1.4 Representation Learning: Part 2",
        "link": "https://www.youtube.com/watch?v=mU6CzvuUM00"
      },
      {
        "id": "1.5 Representation Learning",
        "title": "1.5 Representation Learning: Part 3",
        "link": "https://www.youtube.com/watch?v=t0bA3rsZ6qM"
      },
      {
        "id": "1.6 Principal component analysis",
        "title": "1.6 Principal component analysis: Part 1",
        "link": "https://www.youtube.com/watch?v=_GOADM-SdKU"
      },
      {
        "id": "1.7 Principal component analysis",
        "title": "1.7 Principal component analysis: Part 2",
        "link": "https://www.youtube.com/watch?v=o__dWBLqPhQ"
      },
      {
        "id": "Tutorial Session - Week 1",
        "title": "Tutorial Session - Week 1",
        "link": "https://www.youtube.com/watch?v=BkesMPmhh_E"
      }
    ],
    "Week 2": [
      {
        "id": "2.1 Issues with PCA",
        "title": "2.1 Issues with PCA",
        "link": "https://www.youtube.com/watch?v=sgU4zbO-W4M"
      },
      {
        "id": "2.2 Time-complexity issue with PCA",
        "title": "2.2 Time-complexity issue with PCA",
        "link": "https://www.youtube.com/watch?v=pwpDf2_Pytk"
      },
      {
        "id": "2.3 Feature Transformation",
        "title": "2.3 Feature Transformation",
        "link": "https://www.youtube.com/watch?v=zcxnCyVSh70"
      },
      {
        "id": "2.4 Kernel Functions",
        "title": "2.4 Kernel Functions",
        "link": "https://www.youtube.com/watch?v=G6rMGLhw3IQ"
      },
      {
        "id": "2.5 Kernel PCA",
        "title": "2.5 Kernel PCA",
        "link": "https://www.youtube.com/watch?v=K46tdjqxM0w"
      },
      {
        "id": "Tutorial Session - Week 2",
        "title": "Tutorial Session - Week 2",
        "link": "https://www.youtube.com/watch?v=Qs8dVQzu43I"
      }
    ],
    "Week 3": [
      {
        "id": "3.1 Introduction to Clustering",
        "title": "3.1 Introduction to Clustering",
        "link": "https://www.youtube.com/watch?v=A3UNtCuMm7Y"
      },
      {
        "id": "3.2 K-means Clustering (Lloyd's algorithm)",
        "title": "3.2 K-means Clustering (Lloyd's algorithm)",
        "link": "https://www.youtube.com/watch?v=QrXQ5cMzphA"
      },
      {
        "id": "3.3 Convergence of K-means algorithm",
        "title": "3.3 Convergence of K-means algorithm",
        "link": "https://www.youtube.com/watch?v=5geXmawaImk"
      },
      {
        "id": "3.4 Nature of clusters produced by K-means",
        "title": "3.4 Nature of clusters produced by K-means",
        "link": "https://www.youtube.com/watch?v=EY03QHaaSBY"
      },
      {
        "id": "3.5 Initialization of centroids, K-means++",
        "title": "3.5 Initialization of centroids, K-means++",
        "link": "https://www.youtube.com/watch?v=Cbrdtxq6bdk"
      },
      {
        "id": "3.6 Choice of K",
        "title": "3.6 Choice of K",
        "link": "https://www.youtube.com/watch?v=4-ycWgdMXD4"
      },
      {
        "id": "Tutorial Session - Week 3",
        "title": "Tutorial Session - Week 3",
        "link": "https://www.youtube.com/watch?v=_4mnXtczNoc"
      }
    ],
    "Week 4": [
      {
        "id": "4.1 Introduction to Estimation",
        "title": "4.1 Introduction to Estimation",
        "link": "https://www.youtube.com/watch?v=382yNz5LoX0"
      },
      {
        "id": "4.2 Maximum Likelihood Estimation",
        "title": "4.2 Maximum Likelihood Estimation",
        "link": "https://www.youtube.com/watch?v=9dQSEn0ooTc"
      },
      {
        "id": "4.3 Bayesian estimation",
        "title": "4.3 Bayesian estimation",
        "link": "https://www.youtube.com/watch?v=ZnkRbtZLPm4"
      },
      {
        "id": "4.4 Gaussian Mixture Models",
        "title": "4.4 Gaussian Mixture Models",
        "link": "https://www.youtube.com/watch?v=dyRTVmtML-U"
      },
      {
        "id": "4.5 Likelihood of GMM",
        "title": "4.5 Likelihood of GMM",
        "link": "https://www.youtube.com/watch?v=a-VVrP11ZIo"
      },
      {
        "id": "4.6 Convex functions and Jensen's inequality",
        "title": "4.6 Convex functions and Jensen's inequality",
        "link": "https://www.youtube.com/watch?v=4s0aNldT02Y"
      },
      {
        "id": "4.7 Estimating the parameters",
        "title": "4.7 Estimating the parameters",
        "link": "https://www.youtube.com/watch?v=idWmaE39OIk"
      },
      {
        "id": "4.8 EM algorithm",
        "title": "4.8 EM algorithm",
        "link": "https://www.youtube.com/watch?v=1jSonYih_sM"
      },
      {
        "id": "Tutorial Session - Week 4",
        "title": "Tutorial Session - Week 4",
        "link": "https://www.youtube.com/watch?v=iC215XRWABA"
      }
    ],
    "Week 5": [
      {
        "id": "5.1 Supervised Learning",
        "title": "5.1 Supervised Learning",
        "link": "https://www.youtube.com/watch?v=AIKTk9KtPJ0"
      },
      {
        "id": "5.2 Linear Regression",
        "title": "5.2 Linear Regression",
        "link": "https://www.youtube.com/watch?v=RkcCmmN0TY4"
      },
      {
        "id": "5.3 Optimizing the error function",
        "title": "5.3 Optimizing the error function",
        "link": "https://www.youtube.com/watch?v=JQPLz5YhjaM"
      },
      {
        "id": "5.4 Geometric interpretation of linear regression",
        "title": "5.4 Geometric interpretation of linear regression",
        "link": "https://www.youtube.com/watch?v=SGbelq087Qs"
      },
      {
        "id": "5.5 Gradient descent",
        "title": "5.5 Gradient descent",
        "link": "https://www.youtube.com/watch?v=vS1LK8xoM4g"
      },
      {
        "id": "5.6 Kernel regression",
        "title": "5.6 Kernel regression",
        "link": "https://www.youtube.com/watch?v=u9ir3yQynpE"
      },
      {
        "id": "5.7 Probabilistic view of linear regression",
        "title": "5.7 Probabilistic view of linear regression",
        "link": "https://www.youtube.com/watch?v=gLGQokSrtDI"
      },
      {
        "id": "Tutorial Session - Week 5",
        "title": "Tutorial Session - Week 5",
        "link": "https://www.youtube.com/watch?v=mZbr0r6V6JI"
      }
    ],
    "Week 6": [
      {
        "id": "6.1 Goodness of Maximum Likelihood Estimator for linear regression",
        "title": "6.1 Goodness of Maximum Likelihood Estimator for linear regression",
        "link": "https://www.youtube.com/watch?v=_CNCiGfwdQs"
      },
      {
        "id": "6.2 Cross-validation for minimizing MSE",
        "title": "6.2 Cross-validation for minimizing MSE",
        "link": "https://www.youtube.com/watch?v=_hmPiYKlRTQ"
      },
      {
        "id": "6.3 Bayesian Modeling for linear regression",
        "title": "6.3 Bayesian Modeling for linear regression",
        "link": "https://www.youtube.com/watch?v=DG7KvatwL2Q"
      },
      {
        "id": "6.4 Ridge regression",
        "title": "6.4 Ridge regression",
        "link": "https://www.youtube.com/watch?v=dMB1c5NADnE"
      },
      {
        "id": "6.5 Relation between solution of linear regression and ridge regression",
        "title": "6.5 Relation between solution of linear regression and ridge regression",
        "link": "https://www.youtube.com/watch?v=rCfjaEYxaC8"
      },
      {
        "id": "6.6 Relation between solution of linear regression and Lasso regression",
        "title": "6.6 Relation between solution of linear regression and Lasso regression",
        "link": "https://www.youtube.com/watch?v=f9KWAixPUCc"
      },
      {
        "id": "6.7 Characteristics of Lasso regression",
        "title": "6.7 Characteristics of Lasso regression",
        "link": "https://www.youtube.com/watch?v=79eeNk7InHk"
      },
      {
        "id": "Tutorial Session - Week 6",
        "title": "Tutorial Session - Week 6",
        "link": "https://www.youtube.com/watch?v=YziPX5i9trQ"
      }
    ],
    "Week 7": [
      {
        "id": "L7.1 Introduction to Binary Classification",
        "title": "L7.1 Introduction to Binary Classification",
        "link": "https://www.youtube.com/watch?v=_w9irUy_8Cs"
      },
      {
        "id": "L7.2 K-Nearest Neighbours",
        "title": "L7.2 K-Nearest Neighbours",
        "link": "https://www.youtube.com/watch?v=H-Y_A7HvBqk"
      },
      {
        "id": "L7.3 Introduction to Decision Trees",
        "title": "L7.3 Introduction to Decision Trees",
        "link": "https://www.youtube.com/watch?v=gXbAJGd8fO0"
      },
      {
        "id": "L7.4 Decision Tree Algorithm",
        "title": "L7.4 Decision Tree Algorithm",
        "link": "https://www.youtube.com/watch?v=5rnu6Hvbt8I"
      },
      {
        "id": "L7.5 Generative and Discriminative Models",
        "title": "L7.5 Generative and Discriminative Models",
        "link": "https://www.youtube.com/watch?v=gwa47ZzhYno"
      }
    ],
    "Week 8": [
      {
        "id": "L8.1 Generative model-based algorithm",
        "title": "L8.1 Generative model-based algorithm",
        "link": "https://www.youtube.com/watch?v=tna8wxoasss"
      },
      {
        "id": "L8.2 Alternate generative model-based algorithm",
        "title": "L8.2 Alternate generative model-based algorithm",
        "link": "https://www.youtube.com/watch?v=GdYLuJqHZAc"
      },
      {
        "id": "L8.3 Naive Bayes algorithm",
        "title": "L8.3 Naive Bayes algorithm",
        "link": "https://www.youtube.com/watch?v=VKqGflpKG_A"
      },
      {
        "id": "L8.4 Pitfalls of naive Bayes algorithm",
        "title": "L8.4 Pitfalls of naive Bayes algorithm",
        "link": "https://www.youtube.com/watch?v=RuE8SQajgxY"
      },
      {
        "id": "L8.5 Decision function of naive Bayes",
        "title": "L8.5 Decision function of naive Bayes",
        "link": "https://www.youtube.com/watch?v=ADXQaTI0Lpo"
      },
      {
        "id": "L8.6 Gaussian naive Bayes",
        "title": "L8.6 Gaussian naive Bayes",
        "link": "https://www.youtube.com/watch?v=oTMYU7hC2bw"
      }
    ],
    "Week 9": [
      {
        "id": "L9.1 Perceptron Learning Algorithm",
        "title": "L9.1 Perceptron Learning Algorithm",
        "link": "https://www.youtube.com/watch?v=G7tYdl0Osf4"
      },
      {
        "id": "L9.2 Understanding Perceptron Update Rule",
        "title": "L9.2 Understanding Perceptron Update Rule",
        "link": "https://www.youtube.com/watch?v=FMRpmR9HNtY"
      },
      {
        "id": "L9.3 Proof of convergence of Perceptron Algorithm",
        "title": "L9.3 Proof of convergence of Perceptron Algorithm",
        "link": "https://www.youtube.com/watch?v=fHDouTKwfXw"
      },
      {
        "id": "L9.4 Sigmoid function for modeling class probabilities",
        "title": "L9.4 Sigmoid function for modeling class probabilities",
        "link": "https://www.youtube.com/watch?v=udFWtBLJUvA"
      },
      {
        "id": "L9.5 Logistic Regression",
        "title": "L9.5 Logistic Regression",
        "link": "https://www.youtube.com/watch?v=bb4yn4RssLs"
      }
    ],
    "Week 10": [
      {
        "id": "L10.1 Perceptrons and Margin",
        "title": "L10.1 Perceptrons and Margin",
        "link": "https://www.youtube.com/watch?v=-guLBqucS_I"
      },
      {
        "id": "L10.2 Maximum margin",
        "title": "L10.2 Maximum margin: Formulation",
        "link": "https://www.youtube.com/watch?v=ZzWFdt_6KLA"
      },
      {
        "id": "L10.3 Constrained Optimization",
        "title": "L10.3 Constrained Optimization",
        "link": "https://www.youtube.com/watch?v=7Th2YgPMnk0"
      },
      {
        "id": "L10.4 Formulating the Dual Problem",
        "title": "L10.4 Formulating the Dual Problem",
        "link": "https://www.youtube.com/watch?v=85BxDKkiK4c"
      },
      {
        "id": "L10.5 Support Vector Machine",
        "title": "L10.5 Support Vector Machine",
        "link": "https://www.youtube.com/watch?v=2LnQ2r7Q3-0"
      },
      {
        "id": "L10.6 Soft Margin SVM",
        "title": "L10.6 Soft Margin SVM",
        "link": "https://www.youtube.com/watch?v=leolYGmaFLM"
      }
    ],
    "Week 11": [
      {
        "id": "L11.1 Dual formulation for Soft Margin SVM",
        "title": "L11.1 Dual formulation for Soft Margin SVM",
        "link": "https://www.youtube.com/watch?v=MZzp4OP8GgQ"
      },
      {
        "id": "L11.2 Complementary slackness conditions for soft-margin SVM",
        "title": "L11.2 Complementary slackness conditions for soft-margin SVM",
        "link": "https://www.youtube.com/watch?v=jthjk2nboDM"
      },
      {
        "id": "L11.3 Summary for soft-margin SVM",
        "title": "L11.3 Summary for soft-margin SVM",
        "link": "https://www.youtube.com/watch?v=jbcaJ_kn3CQ"
      },
      {
        "id": "L11.4 Overfitting and underfitting",
        "title": "L11.4 Overfitting and underfitting",
        "link": "https://www.youtube.com/watch?v=VcrPtcJWvDE"
      },
      {
        "id": "L11.5 Bagging",
        "title": "L11.5 Bagging",
        "link": "https://www.youtube.com/watch?v=OXTu2vrsTjY"
      },
      {
        "id": "L11.6 Boosting",
        "title": "L11.6 Boosting",
        "link": "https://www.youtube.com/watch?v=-B534pLpnhk"
      }
    ],
    "Week 12": [
      {
        "id": "L12.1 Classification Loss functions",
        "title": "L12.1 Classification Loss functions",
        "link": "https://www.youtube.com/watch?v=1ok_K5EohoU"
      },
      {
        "id": "L12.2 SVM and Logistic Loss",
        "title": "L12.2 SVM and Logistic Loss",
        "link": "https://www.youtube.com/watch?v=tXVelGBsIPI"
      },
      {
        "id": "L12.3 Perceptron and Boosting Loss",
        "title": "L12.3 Perceptron and Boosting Loss",
        "link": "https://www.youtube.com/watch?v=ZAuZqOM-skQ"
      },
      {
        "id": "L12.4 Neural Networks",
        "title": "L12.4 Neural Networks",
        "link": "https://www.youtube.com/watch?v=Y6CNz0wRWpI"
      },
      {
        "id": "L12.5 Computing parameters of a neural network",
        "title": "L12.5 Computing parameters of a neural network",
        "link": "https://www.youtube.com/watch?v=LctgFHD_RN4"
      },
      {
        "id": "L12.6 Summary of the course and future directions",
        "title": "L12.6 Summary of the course and future directions",
        "link": "https://www.youtube.com/watch?v=06PP-3xUCs0"
      }
    ]
  }
}
